fanfou/__init__.py
fanfou/api.py
fanfou/backup.py
fanfou/backupcmd.py
fanfou/backupui.py
fanfou/basedb.py
fanfou/config.py
fanfou/const.py
fanfou/db.py
fanfou/renderer.py
fanfou/template.py
fanfou/utils.py
fanfou/xauth.py
pyfanfou-1.0.2.dist-info/DESCRIPTION.rst
pyfanfou-1.0.2.dist-info/entry_points.txt
pyfanfou-1.0.2.dist-info/METADATA
pyfanfou-1.0.2.dist-info/metadata.json
pyfanfou-1.0.2.dist-info/RECORD
pyfanfou-1.0.2.dist-info/top_level.txt
pyfanfou-1.0.2.dist-info/WHEEL
