Metadata-Version: 2.0
Name: pyfanfou
Version: 1.0.2
Summary: 饭否数据备份工具
Home-page: https://github.com/mcxiaoke/pyfanfou
Author: Xiaoke Zhang
Author-email: mail@mcxiaoke.com
License: Apache License 2.0
Keywords: fanfou.com,fanfou,backup,Tkinter
Platform: UNKNOWN
Classifier: Development Status :: 4 - Beta
Classifier: Operating System :: OS Independent
Classifier: Programming Language :: Python :: 2.6
Classifier: Programming Language :: Python :: 2.7
Classifier: Topic :: Utilities
Requires-Dist: requests
Requires-Dist: oauth2
Requires-Dist: requests-oauthlib
